<?xml version = '1.0' encoding = 'UTF-8'?>
<Diagram class="oracle.dbtools.crest.swingui.relational.DPVRelational" name="Relational_1" id="E0EE16C4-4816-AC2A-5CF5-FE38B1BDC1FC">
<createdBy>quind</createdBy>
<modifiedBy>quind</modifiedBy>
<createdTime>2019-09-22 02:11:36 UTC</createdTime>
<autoRoute>false</autoRoute>
<boxInbox>true</boxInbox>
<showLegend>false</showLegend>
<showLabels>false</showLabels>
<showRelAttributes>false</showRelAttributes>
<gridEnabled>false</gridEnabled>
<showGrid>false</showGrid>
<diagramColor>-1</diagramColor>
<display>false</display>
<notation>1</notation>
<objectViews>
<OView class="oracle.dbtools.crest.swingui.relational.TVTable" oid="07F7C8AC-8422-F798-0097-55481F076C4C" otype="Table" vid="3487BD71-B868-3EC3-03B7-D3E6339CF4ED">
<hideElementsInCurrentOnly>false</hideElementsInCurrentOnly>
<bounds x="486" y="602" width="207" height="111"/>
</OView>
<OView class="oracle.dbtools.crest.swingui.relational.TVTable" oid="15DAE48A-B252-AAAD-CB40-AE52A5E2D77A" otype="Table" vid="A8B48E13-4F6B-065E-631E-4322760DD7A5">
<hideElementsInCurrentOnly>false</hideElementsInCurrentOnly>
<bounds x="164" y="730" width="234" height="114"/>
</OView>
<OView class="oracle.dbtools.crest.swingui.relational.TVTable" oid="2A4BAB88-7F08-94ED-DF76-A565415750DB" otype="Table" vid="72197573-4616-3E9E-5682-4191BB15AF6A">
<hideElementsInCurrentOnly>false</hideElementsInCurrentOnly>
<bounds x="484" y="298" width="225" height="89"/>
</OView>
<OView class="oracle.dbtools.crest.swingui.relational.TVTable" oid="2BABA4E3-36FA-2A70-4B4C-421695C8452C" otype="Table" vid="287CBAF4-F3FF-9BF0-C1C8-41EF163C7257">
<hideElementsInCurrentOnly>false</hideElementsInCurrentOnly>
<bounds x="139" y="568" width="309" height="124"/>
</OView>
<OView class="oracle.dbtools.crest.swingui.relational.TVTable" oid="2CB1007C-4715-FC1B-CC66-2EFC812C8FC1" otype="Table" vid="FBA36150-D7A5-FC5C-E9F2-3567BDE52F99">
<hideElementsInCurrentOnly>false</hideElementsInCurrentOnly>
<bounds x="1113" y="384" width="239" height="100"/>
</OView>
<OView class="oracle.dbtools.crest.swingui.relational.TVTable" oid="5A1E3624-A312-3D5C-EAA3-C60243AA0EA5" otype="Table" vid="3DF872DF-1CF6-06B8-44B0-6116EE8BBB35">
<hideElementsInCurrentOnly>false</hideElementsInCurrentOnly>
<bounds x="1026" y="130" width="170" height="111"/>
</OView>
<OView class="oracle.dbtools.crest.swingui.relational.TVTable" oid="7C6B1ED4-71AE-864C-57EB-3072066EA04D" otype="Table" vid="60700064-FD79-5B43-FB58-AC47F7DA724B">
<hideElementsInCurrentOnly>false</hideElementsInCurrentOnly>
<bounds x="192" y="876" width="170" height="113"/>
</OView>
<OView class="oracle.dbtools.crest.swingui.relational.TVTable" oid="8B6E5AB7-59F0-FB1B-A78F-E9EF2AD1FEDC" otype="Table" vid="637433B0-B311-DE67-9FBA-A418E4732E48">
<hideElementsInCurrentOnly>false</hideElementsInCurrentOnly>
<bounds x="492" y="436" width="227" height="98"/>
</OView>
<OView class="oracle.dbtools.crest.swingui.relational.TVTable" oid="95EEA337-B42D-EF8A-0901-A6A5EA376D73" otype="Table" vid="0E279E29-22BA-84F7-174D-AF4B7080C184">
<hideElementsInCurrentOnly>false</hideElementsInCurrentOnly>
<bounds x="403" y="12" width="272" height="163"/>
</OView>
<OView class="oracle.dbtools.crest.swingui.relational.TVTable" oid="A569A444-5362-5460-6FAF-5E82D06DDCF7" otype="Table" vid="4DBAEBC7-B786-AFEA-1BA5-9D710F08EC59">
<hideElementsInCurrentOnly>false</hideElementsInCurrentOnly>
<bounds x="1241" y="68" width="397" height="164"/>
</OView>
<OView class="oracle.dbtools.crest.swingui.relational.TVTable" oid="BCBE2919-3D52-2DB8-C4E0-F72CEB478760" otype="Table" vid="F0084322-1A97-7F0A-B689-2D88D6408854">
<hideElementsInCurrentOnly>false</hideElementsInCurrentOnly>
<bounds x="1731" y="100" width="170" height="110"/>
</OView>
<OView class="oracle.dbtools.crest.swingui.relational.TVTable" oid="C6D4EB11-D73D-FFD3-6516-A3004D4DA15A" otype="Table" vid="59392E3C-D595-9EB2-D3AD-E420050321F8">
<hideElementsInCurrentOnly>false</hideElementsInCurrentOnly>
<bounds x="1146" y="605" width="333" height="111"/>
</OView>
<OView class="oracle.dbtools.crest.swingui.relational.TVTable" oid="CC4400D4-1DE0-7854-4DE6-ECF6FC31656B" otype="Table" vid="03355A7D-9634-3764-505A-D939684A2F93">
<hideElementsInCurrentOnly>false</hideElementsInCurrentOnly>
<bounds x="755" y="400" width="232" height="111"/>
</OView>
<OView class="oracle.dbtools.crest.swingui.relational.TVTable" oid="D2917817-A9F4-6C9F-410C-D01D4E1DA70D" otype="Table" vid="5387AD8D-293E-8013-C366-D80F52813A59">
<hideElementsInCurrentOnly>false</hideElementsInCurrentOnly>
<bounds x="773" y="569" width="315" height="111"/>
</OView>
<OView class="oracle.dbtools.crest.swingui.relational.TVTable" oid="D7CD6494-1758-F055-8656-2BF253D8BB44" otype="Table" vid="A26100F2-87EE-6B7A-347F-A851C9855017">
<hideElementsInCurrentOnly>false</hideElementsInCurrentOnly>
<bounds x="1389" y="318" width="339" height="130"/>
</OView>
<OView class="oracle.dbtools.crest.swingui.relational.TVTable" oid="DF3624CC-C8AD-B483-D3D1-F08CEC32434E" otype="Table" vid="A349A6E2-96D1-9F0A-0457-96B62C4CF049">
<hideElementsInCurrentOnly>false</hideElementsInCurrentOnly>
<bounds x="100" y="198" width="284" height="332"/>
</OView>
<OView class="oracle.dbtools.crest.swingui.relational.TVTable" oid="E4919AAD-A93B-ED8D-A1B3-C4EC4D78E20C" otype="Table" vid="204F82BE-4525-CF28-A67E-303594F85748">
<hideElementsInCurrentOnly>false</hideElementsInCurrentOnly>
<bounds x="724" y="118" width="265" height="255"/>
</OView>
</objectViews>
<connectors>
<Connector class="oracle.dbtools.crest.swingui.relational.TVFKRelation" oid="085F0B2F-FD17-B2A0-79D7-522713496A03" otype="FKIndexAssociation" vid_source="A8B48E13-4F6B-065E-631E-4322760DD7A5" vid_target="287CBAF4-F3FF-9BF0-C1C8-41EF163C7257">
<hideElementsInCurrentOnly>false</hideElementsInCurrentOnly>
<backgroundColor>-16777216</backgroundColor>
<lineWidth>1</lineWidth>
<points>
<point x="281" y="730"/>
<point x="281" y="692"/>
</points>
</Connector>
<Connector class="oracle.dbtools.crest.swingui.relational.TVFKRelation" oid="128D9C42-DCC1-B7D0-BDC7-DFFBB77738F0" otype="FKIndexAssociation" vid_source="4DBAEBC7-B786-AFEA-1BA5-9D710F08EC59" vid_target="A26100F2-87EE-6B7A-347F-A851C9855017">
<hideElementsInCurrentOnly>false</hideElementsInCurrentOnly>
<backgroundColor>-16777216</backgroundColor>
<lineWidth>1</lineWidth>
<points>
<point x="1513" y="232"/>
<point x="1513" y="318"/>
</points>
</Connector>
<Connector class="oracle.dbtools.crest.swingui.relational.TVFKRelation" oid="24186497-73F2-4A01-9643-695E57681CE8" otype="FKIndexAssociation" vid_source="4DBAEBC7-B786-AFEA-1BA5-9D710F08EC59" vid_target="0E279E29-22BA-84F7-174D-AF4B7080C184">
<hideElementsInCurrentOnly>false</hideElementsInCurrentOnly>
<backgroundColor>-16777216</backgroundColor>
<lineWidth>1</lineWidth>
<points>
<point x="1241" y="121"/>
<point x="675" y="121"/>
</points>
</Connector>
<Connector class="oracle.dbtools.crest.swingui.relational.TVFKRelation" oid="2805259E-4B06-009D-9B86-C05D51C46B59" otype="FKIndexAssociation" vid_source="A349A6E2-96D1-9F0A-0457-96B62C4CF049" vid_target="0E279E29-22BA-84F7-174D-AF4B7080C184">
<hideElementsInCurrentOnly>false</hideElementsInCurrentOnly>
<backgroundColor>-16777216</backgroundColor>
<lineWidth>1</lineWidth>
<points>
<point x="384" y="234"/>
<point x="449" y="175"/>
</points>
</Connector>
<Connector class="oracle.dbtools.crest.swingui.relational.TVFKRelation" oid="336EC698-568D-F5C2-3212-F97715724B04" otype="FKIndexAssociation" vid_source="A26100F2-87EE-6B7A-347F-A851C9855017" vid_target="F0084322-1A97-7F0A-B689-2D88D6408854">
<hideElementsInCurrentOnly>false</hideElementsInCurrentOnly>
<backgroundColor>-16777216</backgroundColor>
<lineWidth>1</lineWidth>
<points>
<point x="1631" y="318"/>
<point x="1753" y="210"/>
</points>
</Connector>
<Connector class="oracle.dbtools.crest.swingui.relational.TVFKRelation" oid="388B7EBF-2F2F-75EC-70B1-2AAB08D9CEA7" otype="FKIndexAssociation" vid_source="A349A6E2-96D1-9F0A-0457-96B62C4CF049" vid_target="3487BD71-B868-3EC3-03B7-D3E6339CF4ED">
<hideElementsInCurrentOnly>false</hideElementsInCurrentOnly>
<backgroundColor>-16777216</backgroundColor>
<lineWidth>1</lineWidth>
<points>
<point x="384" y="483"/>
<point x="538" y="602"/>
</points>
</Connector>
<Connector class="oracle.dbtools.crest.swingui.relational.TVFKRelation" oid="40A03E89-6540-CEDF-A8ED-610E9BD63FBF" otype="FKIndexAssociation" vid_source="60700064-FD79-5B43-FB58-AC47F7DA724B" vid_target="A8B48E13-4F6B-065E-631E-4322760DD7A5">
<hideElementsInCurrentOnly>false</hideElementsInCurrentOnly>
<backgroundColor>-16777216</backgroundColor>
<lineWidth>1</lineWidth>
<points>
<point x="277" y="876"/>
<point x="277" y="844"/>
</points>
</Connector>
<Connector class="oracle.dbtools.crest.swingui.relational.TVFKRelation" oid="4C634DF3-12C6-B225-7D4C-8E7D289911B5" otype="FKIndexAssociation" vid_source="03355A7D-9634-3764-505A-D939684A2F93" vid_target="5387AD8D-293E-8013-C366-D80F52813A59">
<hideElementsInCurrentOnly>false</hideElementsInCurrentOnly>
<backgroundColor>-16777216</backgroundColor>
<lineWidth>1</lineWidth>
<points>
<point x="880" y="511"/>
<point x="880" y="569"/>
</points>
</Connector>
<Connector class="oracle.dbtools.crest.swingui.relational.TVFKRelation" oid="6609D0BA-CA73-36A6-EA95-8EF250A18253" otype="FKIndexAssociation" vid_source="5387AD8D-293E-8013-C366-D80F52813A59" vid_target="3487BD71-B868-3EC3-03B7-D3E6339CF4ED">
<hideElementsInCurrentOnly>false</hideElementsInCurrentOnly>
<backgroundColor>-16777216</backgroundColor>
<lineWidth>1</lineWidth>
<points>
<point x="773" y="656"/>
<point x="693" y="656"/>
</points>
</Connector>
<Connector class="oracle.dbtools.crest.swingui.relational.TVFKRelation" oid="71DBE079-37BB-1040-DCAD-15065862F751" otype="FKIndexAssociation" vid_source="637433B0-B311-DE67-9FBA-A418E4732E48" vid_target="A349A6E2-96D1-9F0A-0457-96B62C4CF049">
<hideElementsInCurrentOnly>false</hideElementsInCurrentOnly>
<backgroundColor>-16777216</backgroundColor>
<lineWidth>1</lineWidth>
<points>
<point x="492" y="498"/>
<point x="384" y="498"/>
</points>
</Connector>
<Connector class="oracle.dbtools.crest.swingui.relational.TVFKRelation" oid="872CF526-CFF1-281F-7468-4304133E41DB" otype="FKIndexAssociation" vid_source="287CBAF4-F3FF-9BF0-C1C8-41EF163C7257" vid_target="A349A6E2-96D1-9F0A-0457-96B62C4CF049">
<hideElementsInCurrentOnly>false</hideElementsInCurrentOnly>
<backgroundColor>-16777216</backgroundColor>
<lineWidth>1</lineWidth>
<points>
<point x="261" y="568"/>
<point x="261" y="530"/>
</points>
</Connector>
<Connector class="oracle.dbtools.crest.swingui.relational.TVFKRelation" oid="902BB781-AF85-7A82-0487-B1F0BB96ADBF" otype="FKIndexAssociation" vid_source="204F82BE-4525-CF28-A67E-303594F85748" vid_target="3DF872DF-1CF6-06B8-44B0-6116EE8BBB35">
<hideElementsInCurrentOnly>false</hideElementsInCurrentOnly>
<backgroundColor>-16777216</backgroundColor>
<lineWidth>1</lineWidth>
<points>
<point x="989" y="185"/>
<point x="1026" y="185"/>
</points>
</Connector>
<Connector class="oracle.dbtools.crest.swingui.relational.TVFKRelation" oid="936DA066-9740-FF16-83E6-BD0A5CA557E5" otype="FKIndexAssociation" vid_source="204F82BE-4525-CF28-A67E-303594F85748" vid_target="0E279E29-22BA-84F7-174D-AF4B7080C184">
<hideElementsInCurrentOnly>false</hideElementsInCurrentOnly>
<backgroundColor>-16777216</backgroundColor>
<lineWidth>1</lineWidth>
<points>
<point x="724" y="146"/>
<point x="675" y="146"/>
</points>
</Connector>
<Connector class="oracle.dbtools.crest.swingui.relational.TVFKRelation" oid="ACC60E40-0746-ADAE-D4B1-A87EFC269289" otype="FKIndexAssociation" vid_source="FBA36150-D7A5-FC5C-E9F2-3567BDE52F99" vid_target="4DBAEBC7-B786-AFEA-1BA5-9D710F08EC59">
<hideElementsInCurrentOnly>false</hideElementsInCurrentOnly>
<backgroundColor>-16777216</backgroundColor>
<lineWidth>1</lineWidth>
<points>
<point x="1296" y="384"/>
<point x="1296" y="232"/>
</points>
</Connector>
<Connector class="oracle.dbtools.crest.swingui.relational.TVFKRelation" oid="BDFBCA42-377C-7891-E2FD-E0D67E5ACC9A" otype="FKIndexAssociation" vid_source="03355A7D-9634-3764-505A-D939684A2F93" vid_target="204F82BE-4525-CF28-A67E-303594F85748">
<hideElementsInCurrentOnly>false</hideElementsInCurrentOnly>
<backgroundColor>-16777216</backgroundColor>
<lineWidth>1</lineWidth>
<points>
<point x="871" y="400"/>
<point x="871" y="373"/>
</points>
</Connector>
<Connector class="oracle.dbtools.crest.swingui.relational.TVFKRelation" oid="BF566520-A415-5177-7F0F-610233924C0D" otype="FKIndexAssociation" vid_source="FBA36150-D7A5-FC5C-E9F2-3567BDE52F99" vid_target="59392E3C-D595-9EB2-D3AD-E420050321F8">
<hideElementsInCurrentOnly>false</hideElementsInCurrentOnly>
<backgroundColor>-16777216</backgroundColor>
<lineWidth>1</lineWidth>
<points>
<point x="1264" y="484"/>
<point x="1264" y="605"/>
</points>
</Connector>
<Connector class="oracle.dbtools.crest.swingui.relational.TVFKRelation" oid="C9BC77D0-EE38-77BF-687F-53FD9FD7D313" otype="FKIndexAssociation" vid_source="72197573-4616-3E9E-5682-4191BB15AF6A" vid_target="A349A6E2-96D1-9F0A-0457-96B62C4CF049">
<hideElementsInCurrentOnly>false</hideElementsInCurrentOnly>
<backgroundColor>-16777216</backgroundColor>
<lineWidth>1</lineWidth>
<points>
<point x="484" y="342"/>
<point x="384" y="342"/>
</points>
</Connector>
<Connector class="oracle.dbtools.crest.swingui.relational.TVFKRelation" oid="DB951D8F-58A0-8D54-AA9C-FF12F0C384A7" otype="FKIndexAssociation" vid_source="59392E3C-D595-9EB2-D3AD-E420050321F8" vid_target="A26100F2-87EE-6B7A-347F-A851C9855017">
<hideElementsInCurrentOnly>false</hideElementsInCurrentOnly>
<backgroundColor>-16777216</backgroundColor>
<lineWidth>1</lineWidth>
<points>
<point x="1434" y="605"/>
<point x="1434" y="448"/>
</points>
</Connector>
<Connector class="oracle.dbtools.crest.swingui.relational.TVFKRelation" oid="DCD91EF0-5A50-AEFD-C29D-23CC1B760EE6" otype="FKIndexAssociation" vid_source="4DBAEBC7-B786-AFEA-1BA5-9D710F08EC59" vid_target="3DF872DF-1CF6-06B8-44B0-6116EE8BBB35">
<hideElementsInCurrentOnly>false</hideElementsInCurrentOnly>
<backgroundColor>-16777216</backgroundColor>
<lineWidth>1</lineWidth>
<points>
<point x="1241" y="181"/>
<point x="1196" y="181"/>
</points>
</Connector>
<Connector class="oracle.dbtools.crest.swingui.relational.TVFKRelation" oid="EE9942ED-A058-B7CE-6734-878102475E18" otype="FKIndexAssociation" vid_source="4DBAEBC7-B786-AFEA-1BA5-9D710F08EC59" vid_target="F0084322-1A97-7F0A-B689-2D88D6408854">
<hideElementsInCurrentOnly>false</hideElementsInCurrentOnly>
<backgroundColor>-16777216</backgroundColor>
<lineWidth>1</lineWidth>
<points>
<point x="1638" y="155"/>
<point x="1731" y="155"/>
</points>
</Connector>
</connectors>
</Diagram>
